[
  {
    "component": "fontIcon",
    "config": {
      "i": "item-0",
      "minW": 10,
      "minH": 10,
      "isDraggable": true,
      "isResizable": true,
      "static": false,
      "w": 20,
      "x": 4,
      "y": 1
    }
  },{
    "component": "table",
    "config": {
      "h": 3,
      "i": "item-1",
      "isDraggable": true,
      "isResizable": true,
      "moved": false,
      "static": false,
      "minW": 10,
      "minH": 10,
      "w": 3,
      "x": 1,
      "y": 1
    }
  }
]



